czech_holidays.py
czech_holidays-1.0.0.dist-info/LICENSE
czech_holidays-1.0.0.dist-info/WHEEL
czech_holidays-1.0.0.dist-info/METADATA
czech_holidays-1.0.0.dist-info/RECORD
