Metadata-Version: 2.1
Name: czech-holidays
Version: 1.0.0
Summary: Python package with Czech public holidays
Home-page: https://github.com/honzajavorek/czech-holidays
License: MIT
Author: Honza Javorek
Author-email: mail@honzajavorek.cz
Requires-Python: >=3.7
Classifier: License :: OSI Approved :: MIT License
Classifier: Programming Language :: Python :: 3
Classifier: Programming Language :: Python :: 3.10
Classifier: Programming Language :: Python :: 3.7
Classifier: Programming Language :: Python :: 3.8
Classifier: Programming Language :: Python :: 3.9
Requires-Dist: python-dateutil
Project-URL: Repository, https://github.com/honzajavorek/czech-holidays
